Workbook

Sheet Read Me
B2: LIFE HQ
B3: Your money and your habits, on one dashboard.
B6: HOW IT WORKS
B7: 1. Set your monthly income and a budget per category on the 'Budget' tab (blue cells).
B8: 2. Log spending on the 'Expenses' tab — pick a category from the dropdown, type the amount.
B9: 3. Tick off habits each day on the 'Habits' tab (type an 'x' or anything in the day cell).
B10: 4. The 'Dashboard' tab pulls it all together — budget used, savings progress, habit completion. Nothing to fill in there.
B12: WHAT IT TRACKS FOR YOU
B13: • Budget vs. actual per category, and how much of your income is left.
B14: • Savings goals with automatic % complete.
B15: • Habit completion for the month, your best habit, and total check-ins.
B16: • Your top spending categories, ranked automatically.
... B24: BLUE cell = you fill this GREY cell = calculated for you, don't edit

Sheet Setup
A1: Expense Categories | B1: Habits
A2: Rent / Mortgage | B2: Exercise
A3: Utilities | B3: Read 10 pages
A4: Groceries | B4: Drink water
A5: Dining Out | B5: No junk food
A6: Transport | B6: Sleep by 11
A7: Fuel | B7: Study
A8: Insurance | B8: Meditate
A9: Subscriptions | B9: Steps 8k
A10: Shopping
A11: Health
A12: Entertainment
A13: Savings
A14: Other

Sheet Expenses
A1: Date | B1: Category | C1: Description | D1: Amount
A2: 46235 | B2: Rent / Mortgage | C2: Monthly rent | D2: 650
A3: 46236 | B3: Groceries | C3: Weekly shop | D3: 70
A4: 46237 | B4: Subscriptions | C4: Streaming | D4: 15
A5: 46238 | B5: Dining Out | C5: Dinner w/ friends | D5: 35
A6: 46239 | B6: Fuel | C6: Full tank | D6: 60
A7: 46240 | B7: Groceries | C7: Mid-week top up | D7: 40
A8: 46241 | B8: Utilities | C8: Electric + water | D8: 90
A9: 46243 | B9: Entertainment | C9: Cinema | D9: 18
A10: 46244 | B10: Shopping | C10: New shoes | D10: 80
A11: 46246 | B11: Health | C11: Gym membership | D11: 30
A12: 46248 | B12: Dining Out | C12: Lunch | D12: 14
A13: 46249 | B13: Transport | C13: Bus pass | D13: 25

Sheet Budget
A1: BUDGET
A3: Monthly income: | D3: 1400
A5: Category | B5: Budget | C5: Spent | D5: Remaining | E5: key
A6: ='Setup'!A2 | B6: 650 | C6: =IF($A6="","",SUMIF(Expenses!$B$2:$B$201,$A6,Expenses!$D$2:$D$201)) | D6: =IF($A6="","",N($B6)-$C6) | E6: =IF($C6>0,$C6+ROW()/100000,"")
A7: ='Setup'!A3 | B7: 100 | C7: =IF($A7="","",SUMIF(Expenses!$B$2:$B$201,$A7,Expenses!$D$2:$D$201)) | D7: =IF($A7="","",N($B7)-$C7) | E7: =IF($C7>0,$C7+ROW()/100000,"")
A8: ='Setup'!A4 | B8: 140 | C8: =IF($A8="","",SUMIF(Expenses!$B$2:$B$201,$A8,Expenses!$D$2:$D$201)) | D8: =IF($A8="","",N($B8)-$C8) | E8: =IF($C8>0,$C8+ROW()/100000,"")
A9: ='Setup'!A5 | B9: 60 | C9: =IF($A9="","",SUMIF(Expenses!$B$2:$B$201,$A9,Expenses!$D$2:$D$201)) | D9: =IF($A9="","",N($B9)-$C9) | E9: =IF($C9>0,$C9+ROW()/100000,"")
A10: ='Setup'!A6 | B10: 40 | C10: =IF($A10="","",SUMIF(Expenses!$B$2:$B$201,$A10,Expenses!$D$2:$D$201)) | D10: =IF($A10="","",N($B10)-$C10) | E10: =IF($C10>0,$C10+ROW()/100000,"")
A11: ='Setup'!A7 | B11: 80 | C11: =IF($A11="","",SUMIF(Expenses!$B$2:$B$201,$A11,Expenses!$D$2:$D$201)) | D11: =IF($A11="","",N($B11)-$C11) | E11: =IF($C11>0,$C11+ROW()/100000,"")
A12: ='Setup'!A8 | B12: 50 | C12: =IF($A12="","",SUMIF(Expenses!$B$2:$B$201,$A12,Expenses!$D$2:$D$201)) | D12: =IF($A12="","",N($B12)-$C12) | E12: =IF($C12>0,$C12+ROW()/100000,"")
A13: ='Setup'!A9 | B13: 20 | C13: =IF($A13="","",SUMIF(Expenses!$B$2:$B$201,$A13,Expenses!$D$2:$D$201)) | D13: =IF($A13="","",N($B13)-$C13) | E13: =IF($C13>0,$C13+ROW()/100000,"")
A14: ='Setup'!A10 | B14: 60 | C14: =IF($A14="","",SUMIF(Expenses!$B$2:$B$201,$A14,Expenses!$D$2:$D$201)) | D14: =IF($A14="","",N($B14)-$C14) | E14: =IF($C14>0,$C14+ROW()/100000,"")
A15: ='Setup'!A11 | B15: 40 | C15: =IF($A15="","",SUMIF(Expenses!$B$2:$B$201,$A15,Expenses!$D$2:$D$201)) | D15: =IF($A15="","",N($B15)-$C15) | E15: =IF($C15>0,$C15+ROW()/100000,"")
A16: ='Setup'!A12 | B16: 40 | C16: =IF($A16="","",SUMIF(Expenses!$B$2:$B$201,$A16,Expenses!$D$2:$D$201)) | D16: =IF($A16="","",N($B16)-$C16) | E16: =IF($C16>0,$C16+ROW()/100000,"")
A17: ='Setup'!A13 | B17: 100 | C17: =IF($A17="","",SUMIF(Expenses!$B$2:$B$201,$A17,Expenses!$D$2:$D$201)) | D17: =IF($A17="","",N($B17)-$C17) | E17: =IF($C17>0,$C17+ROW()/100000,"")
A18: ='Setup'!A14 | B18: 30 | C18: =IF($A18="","",SUMIF(Expenses!$B$2:$B$201,$A18,Expenses!$D$2:$D$201)) | D18: =IF($A18="","",N($B18)-$C18) | E18: =IF($C18>0,$C18+ROW()/100000,"")
A19: TOTAL | B19: =SUM(B6:B18) | C19: =SUM(C6:C18) | D19: =B19-C19
A21: SAVINGS GOALS
A22: Goal | B22: Target | C22: Saved | D22: % Done
A23: Emergency fund | B23: 3000 | C23: 1200 | D23: =IF(OR($A23="",$B23=""),"",$C23/$B23)
A24: New laptop | B24: 1500 | C24: 450 | D24: =IF(OR($A24="",$B24=""),"",$C24/$B24)
D25: =IF(OR($A25="",$B25=""),"",$C25/$B25)
D26: =IF(OR($A26="",$B26=""),"",$C26/$B26)
D27: =IF(OR($A27="",$B27=""),"",$C27/$B27)
A28: TOTAL | B28: =SUM(B23:B27) | C28: =SUM(C23:C27) | D28: =IFERROR(C28/B28,"")

Sheet Habits
A1: HABITS
A3: Month: | B3: August 2026
A5: Habit | B5: 1 | C5: 2 | D5: 3 | E5: 4 | F5: 5 | G5: 6 | H5: 7 | I5: 8 | J5: 9 | K5: 10 | L5: 11 | M5: 12 | N5: 13 | O5: 14 | P5: 15 | Q5: 16 | R5: 17 | S5: 18 | T5: 19 | U5: 20 | V5: 21 | W5: 22 | X5: 23 | Y5: 24 | Z5: 25 | AA5: 26 | AB5: 27 | AC5: 28 | AD5: 29 | AE5: 30 | AF5: 31 | AG5: Done | AH5: % Month
A6: ='Setup'!B2 | B6: x | C6: x | E6: x | F6: x | G6: x | H6: x | I6: x | J6: x | K6: x | L6: x | M6: x | N6: x | P6: x | AG6: =COUNTA(B6:AF6) | AH6: =IFERROR($AG6/31,0)
A7: ='Setup'!B3 | B7: x | E7: x | F7: x | H7: x | J7: x | K7: x | L7: x | M7: x | O7: x | P7: x | AG7: =COUNTA(B7:AF7) | AH7: =IFERROR($AG7/31,0)
A8: ='Setup'!B4 | C8: x | D8: x | E8: x | F8: x | G8: x | I8: x | J8: x | K8: x | L8: x | M8: x | P8: x | AG8: =COUNTA(B8:AF8) | AH8: =IFERROR($AG8/31,0)
A9: ='Setup'!B5 | B9: x | C9: x | F9: x | H9: x | I9: x | K9: x | L9: x | M9: x | P9: x | AG9: =COUNTA(B9:AF9) | AH9: =IFERROR($AG9/31,0)
A10: ='Setup'!B6 | C10: x | E10: x | F10: x | G10: x | J10: x | L10: x | AG10: =COUNTA(B10:AF10) | AH10: =IFERROR($AG10/31,0)
A11: ='Setup'!B7 | B11: x | C11: x | E11: x | F11: x | G11: x | H11: x | I11: x | K11: x | L11: x | M11: x | O11: x | P11: x | AG11: =COUNTA(B11:AF11) | AH11: =IFERROR($AG11/31,0)
A12: ='Setup'!B8 | B12: x | F12: x | G12: x | H12: x | K12: x | L12: x | M12: x | N12: x | O12: x | P12: x | AG12: =COUNTA(B12:AF12) | AH12: =IFERROR($AG12/31,0)
A13: ='Setup'!B9 | B13: x | C13: x | D13: x | E13: x | F13: x | I13: x | L13: x | AG13: =COUNTA(B13:AF13) | AH13: =IFERROR($AG13/31,0)

Sheet Dashboard
B2: LIFE HQ — DASHBOARD
B3: Your month at a glance. Everything here fills itself.
B5: Income | D5: Spent | F5: Left to spend
B6: =Budget!$D$3 | D6: =Budget!$C$19 | F6: =IF(Budget!$D$3="","",Budget!$D$3-Budget!$C$19)
B8: Budget used | D8: Saved so far | F8: Savings goal %
B9: =IFERROR(Budget!$C$19/Budget!$B$19,0) | D9: =Budget!$C$28 | F9: =Budget!$D$28
B11: HABITS THIS MONTH
B12: Completion % | D12: Check-ins | F12: Best habit
B13: =IFERROR(SUM(Habits!$AG$6:$AG$13)/(COUNTA(Habits!$A$6:$A$13)*31),0) | D13: =SUM(Habits!$AG$6:$AG$13) | F13: =IFERROR(INDEX(Habits!$A$6:$A$13,MATCH(MAX(Habits!$AG$6:$AG$13),Habits!$AG$6:$AG$13,0)),"-")
B16: TOP SPENDING CATEGORIES
B17: # | C17: Category | D17: Spent
B18: 1 | C18: =IFERROR(INDEX(Budget!$A$6:$A$18,MATCH(LARGE(Budget!$E$6:$E$18,1),Budget!$E$6:$E$18,0)),"—") | D18: =IFERROR(INDEX(Budget!$C$6:$C$18,MATCH(LARGE(Budget!$E$6:$E$18,1),Budget!$E$6:$E$18,0)),"")
B19: 2 | C19: =IFERROR(INDEX(Budget!$A$6:$A$18,MATCH(LARGE(Budget!$E$6:$E$18,2),Budget!$E$6:$E$18,0)),"—") | D19: =IFERROR(INDEX(Budget!$C$6:$C$18,MATCH(LARGE(Budget!$E$6:$E$18,2),Budget!$E$6:$E$18,0)),"")
B20: 3 | C20: =IFERROR(INDEX(Budget!$A$6:$A$18,MATCH(LARGE(Budget!$E$6:$E$18,3),Budget!$E$6:$E$18,0)),"—") | D20: =IFERROR(INDEX(Budget!$C$6:$C$18,MATCH(LARGE(Budget!$E$6:$E$18,3),Budget!$E$6:$E$18,0)),"")
